Workbook

Sheet Executive Summary
A1: QuickCart IaaS vs. PaaS Cost Analysis
A2: Google Cloud, us-central1, on-demand pricing. Inputs are editable on the Inputs & Sources sheet.
A4: Key Results
A5: Metric | B5: PaaS | C5: IaaS | D5: Difference | E5: Decision
A6: Year 1 annual cost | B6: ='Part 3 - Growth & Break-Even'!E6 -> 3992.0223 | C6: ='Part 3 - Growth & Break-Even'!E7 -> 31907.02 | D6: =C6-B6 -> 27914.998 | E6: =IF(B6<C6,"PaaS","IaaS") -> PaaS
A7: Year 2 annual cost | B7: ='Part 3 - Growth & Break-Even'!H6 -> 7176.0668 | C7: ='Part 3 - Growth & Break-Even'!H7 -> 34028.079 | D7: =C7-B7 -> 26852.012 | E7: =IF(B7<C7,"PaaS","IaaS") -> PaaS
A8: Estimated break-even users | D8: ='Part 3 - Growth & Break-Even'!D16 -> 267609.47 | E8: =IF(D8>'Inputs & Sources'!C6,"PaaS through Year 2","Review IaaS") -> PaaS through Year 2
A11: Recommendation
A12: Choose PaaS in Year 1 and continue with PaaS in Year 2. Although the self-managed VM has lower raw infrastructure cost, IaaS requires substantially more operations labor. Under the modeled assumptions, PaaS is lower cost at both 5,000 and 15,000 active users and remains lower cost until approximately the break-even user count shown above. Revisit the decision as scale, staffing, reliability, and discount commitments change.
A18: Model Scope and Caveats
A19: This is a back-of-the-envelope comparison, not a production quote. It excludes network egress, taxes, support, load balancers, observability tooling, backup storage, redundancy/high availability, disaster recovery, and engineering time to migrate. The break-even is a linear extrapolation from two assignment-defined data points and should be treated as directional.

Sheet Inputs & Sources
A1: QuickCart FinOps Model — Inputs & Sources
A2: Blue/yellow cells are scenario inputs. All calculated outputs elsewhere use formulas linked to this sheet.
A4: Business and Labor Assumptions
A5: Assumption | B5: Year 1 | C5: Year 2 | D5: Units | E5: Notes
A6: Active users | B6: 5000 | C6: 15000 | D6: users | E6: Year 2 scenario from assignment
A7: Daily active users | B7: 1000 | C7: 3000 | D7: users | E7: Assumed to scale in proportion to active users
A8: Database size | B8: 100 | C8: 300 | D8: GiB | E8: Year 2 PaaS database cost is modeled as 3x per assignment
A9: Average server CPU usage | B9: 0.25 | C9: 0.25 | D9: % | E9: Starting utilization assumption
A10: App engineer rate | B10: 100 | C10: 100 | D10: $/hour | E10: Used for PaaS management
A11: Cloud operations engineer rate | B11: 130 | C11: 130 | D11: $/hour | E11: Used for IaaS management
A12: PaaS management hours | B12: 2 | C12: 2 | D12: hours/month | E12: Assignment assumption
A13: IaaS management hours | B13: 20 | C13: 20 | D13: hours/month | E13: Assignment assumption
A14: Hours per year | B14: 8760 | C14: 8760 | D14: hours | E14: 24 × 365
A15: Months per year | B15: 12 | C15: 12 | D15: months | E15: Calendar year
A16: Average hours per month | B16: 730 | C16: 730 | D16: hours | E16: 8,760 ÷ 12
A18: Google Cloud Pricing Inputs (us-central1, on-demand)
A19: Service / resource | B19: Rate | C19: Units | D19: Configuration / formula | E19: Source
A20: Cloud SQL vCPU | B20: 0.0413 | C20: $/vCPU-hour | D20: 1 vCPU | E20: https://cloud.google.com/sql/pricing
A21: Cloud SQL memory | B21: 0.007 | C21: $/GiB-hour | D21: 3.75 GiB | E21: https://cloud.google.com/sql/pricing
A22: Cloud SQL SSD storage | B22: 0.000232877 | C22: $/GiB-hour | D22: 100 GiB | E22: https://cloud.google.com/sql/pricing
A23: Cloud Run CPU | B23: 2.4e-05 | C23: $/vCPU-second | D23: 1 vCPU, instance-based billing | E23: https://cloud.google.com/run/pricing
A24: Cloud Run memory | B24: 2.5e-06 | C24: $/GiB-second | D24: 0.5 GiB, instance-based billing | E24: https://cloud.google.com/run/pricing
A25: Compute Engine e2-standard-2 | B25: 0.06701142 | C25: $/hour | D25: 2 vCPU, 8 GiB RAM | E25: https://cloud.google.com/products/compute/pricing/general-purpose
A26: Balanced persistent disk | B26: 0.000136986 | C26: $/GiB-hour | D26: 100 GiB | E26: https://cloud.google.com/compute/disks-image-pricing
A28: Scaling Controls
A29: Control | B29: Value | C29: Units | D29: Explanation
A30: PaaS Year 2 infrastructure multiplier | B30: 3 | C30: x | D30: Compute and database each increase 3x
A31: IaaS Year 2 infrastructure multiplier | B31: 4 | C31: x | D31: Original VM plus three additional VMs
A32: PaaS Year 2 management multiplier | B32: 1 | C32: x | D32: Management remains constant
A33: IaaS Year 2 management multiplier | B33: 1 | C33: x | D33: Assignment does not increase management hours

Sheet Part 1 - PaaS Approach
A1: Part 1 — PaaS Approach (“Costco Model”)
A2: Cloud Run + Cloud SQL, modeled as always-on in us-central1.
A4: Year 1 Cost Estimate
A5: Cost component | B5: Quantity | C5: Rate | D5: Calculation | E5: Monthly Cost | F5: Annual Cost | G5: Notes
A6: Cloud SQL vCPU | B6: 1 | C6: ='Inputs & Sources'!B20 -> 0.0413 | D6: =B6*C6*'Inputs & Sources'!B16 -> 30.149 | E6: =D6 -> 30.149 | F6: =E6*'Inputs & Sources'!B15 -> 361.788 | G6: 1 vCPU
A7: Cloud SQL memory | B7: 3.75 | C7: ='Inputs & Sources'!B21 -> 0.007 | D7: =B7*C7*'Inputs & Sources'!B16 -> 19.1625 | E7: =D7 -> 19.1625 | F7: =E7*'Inputs & Sources'!B15 -> 229.95 | G7: 3.75 GiB
A8: Cloud SQL SSD storage | B8: 100 | C8: ='Inputs & Sources'!B22 -> 0.000232877 | D8: =B8*C8*'Inputs & Sources'!B16 -> 17.000021 | E8: =D8 -> 17.000021 | F8: =E8*'Inputs & Sources'!B15 -> 204.00025 | G8: 100 GiB
A9: Cloud Run CPU | B9: 1 | C9: ='Inputs & Sources'!B23 -> 2.4e-05 | D9: =B9*C9*3600 -> 0.0864 | E9: =D9*'Inputs & Sources'!B16 -> 63.072 | F9: =D9*'Inputs & Sources'!B14 -> 756.864 | G9: 1 vCPU always-on
A10: Cloud Run memory | B10: 0.5 | C10: ='Inputs & Sources'!B24 -> 2.5e-06 | D10: =B10*C10*3600 -> 0.0045 | E10: =D10*'Inputs & Sources'!B16 -> 3.285 | F10: =D10*'Inputs & Sources'!B14 -> 39.42 | G10: 0.5 GiB always-on
A11: Management labor | B11: ='Inputs & Sources'!B12 -> 2 | C11: ='Inputs & Sources'!B10 -> 100 | D11: =B11*C11 -> 200 | E11: =D11 -> 200 | F11: =E11*'Inputs & Sources'!B15 -> 2400 | G11: 2 hours/month × app engineer rate
A13: Database subtotal | E13: =SUM(E6:E8) -> 66.311521 | F13: =SUM(F6:F8) -> 795.73825
A14: Compute subtotal | E14: =SUM(E9:E10) -> 66.357 | F14: =SUM(F9:F10) -> 796.284
A15: Total Year 1 PaaS cost | E15: =SUM(E13:E14)+E11 -> 332.66852 | F15: =SUM(F13:F14)+F11 -> 3992.0223
A18: Interpretation
A19: PaaS has higher unit infrastructure pricing than a bare VM, but the managed platform sharply reduces recurring operations labor. Cloud Run handles container infrastructure and autoscaling, while Cloud SQL handles database patching, backups, and managed operations. The model excludes network egress, load balancing, taxes, and support plans.

Sheet Part 2 - IaaS Approach
A1: Part 2 — IaaS Approach (“Leased Farm”)
A2: Compute Engine e2-standard-2 + 100 GiB balanced persistent disk, self-managed.
A4: Year 1 Cost Estimate
A5: Cost component | B5: Quantity | C5: Rate | D5: Calculation | E5: Monthly Cost | F5: Annual Cost | G5: Notes
A6: Compute Engine VM | B6: 1 | C6: ='Inputs & Sources'!B25 -> 0.06701142 | D6: =B6*C6 -> 0.06701142 | E6: =D6*'Inputs & Sources'!B16 -> 48.918337 | F6: =D6*'Inputs & Sources'!B14 -> 587.02004 | G6: e2-standard-2, always on
A7: Balanced persistent disk | B7: 100 | C7: ='Inputs & Sources'!B26 -> 0.000136986 | D7: =B7*C7 -> 0.0136986 | E7: =D7*'Inputs & Sources'!B16 -> 9.999978 | F7: =D7*'Inputs & Sources'!B14 -> 119.99974 | G7: 100 GiB
A8: Management labor | B8: ='Inputs & Sources'!B13 -> 20 | C8: ='Inputs & Sources'!B11 -> 130 | D8: =B8*C8 -> 2600 | E8: =D8 -> 2600 | F8: =E8*'Inputs & Sources'!B15 -> 31200 | G8: 20 hours/month × cloud ops rate
A10: Infrastructure subtotal | E10: =SUM(E6:E7) -> 58.918315 | F10: =SUM(F6:F7) -> 707.01978
A11: Total Year 1 IaaS cost | E11: =E10+E8 -> 2658.9183 | F11: =F10+F8 -> 31907.02
A14: Interpretation
A15: The raw VM and disk cost is low, but the assignment’s 20 hours per month of cloud operations work dominates total cost. That labor covers operating-system patching, security updates, database administration, backup testing, monitoring, incident response, and manual scaling. This estimate does not include a separate load balancer, backup storage, network egress, or redundancy.

Sheet Part 3 - Growth & Break-Even
A1: Parts 3 & 4 — Growth and Break-Even Analysis
A2: Year 2 scaling assumptions follow the assignment exactly. Break-even uses linear interpolation/extrapolation between Year 1 and Year 2.
A4: Year 1 vs. Year 2 Summary
A5: Model | B5: Year 1 Users | C5: Year 1 Infrastructure | D5: Year 1 Management | E5: Year 1 Total | F5: Year 2 Users | G5: Year 2 Infrastructure | H5: Year 2 Total
A6: PaaS | B6: ='Inputs & Sources'!B6 -> 5000 | C6: ='Part 1 - PaaS Approach'!F13+'Part 1 - PaaS Approach'!F14 -> 1592.0223 | D6: ='Part 1 - PaaS Approach'!F11 -> 2400 | E6: ='Part 1 - PaaS Approach'!F15 -> 3992.0223 | F6: ='Inputs & Sources'!C6 -> 15000 | G6: =C6*'Inputs & Sources'!B30 -> 4776.0668 | H6: =G6+(D6*'Inputs & Sources'!B32) -> 7176.0668
A7: IaaS | B7: ='Inputs & Sources'!B6 -> 5000 | C7: ='Part 2 - IaaS Approach'!F10 -> 707.01978 | D7: ='Part 2 - IaaS Approach'!F8 -> 31200 | E7: ='Part 2 - IaaS Approach'!F11 -> 31907.02 | F7: ='Inputs & Sources'!C6 -> 15000 | G7: =C7*'Inputs & Sources'!B31 -> 2828.0791 | H7: =G7+(D7*'Inputs & Sources'!B33) -> 34028.079
A10: Break-Even Calculation
A11: Metric | B11: PaaS | C11: IaaS | D11: Difference / Result | E11: Units
A12: Year 1 total | B12: =E6 -> 3992.0223 | C12: =E7 -> 31907.02 | D12: =C12-B12 -> 27914.998 | E12: $/year
A13: Year 2 total | B13: =H6 -> 7176.0668 | C13: =H7 -> 34028.079 | D13: =C13-B13 -> 26852.012 | E13: $/year
A14: Cost slope per additional user | B14: =(B13-B12)/(F6-B6) -> 0.31840445 | C14: =(C13-C12)/(F7-B7) -> 0.21210593 | D14: =C14-B14 -> -0.10629852 | E14: $/user/year
A15: Intercept | B15: =B12-(B14*B6) -> 2400 | C15: =C12-(C14*B7) -> 30846.49 | D15: =C15-B15 -> 28446.49 | E15: $
A16: Estimated break-even users | D16: =(C15-B15)/(B14-C14) -> 267609.47 | E16: active users
A17: PaaS cost at break-even | D17: =B15+(B14*D16) -> 87608.046 | E17: $/year
A18: IaaS cost at break-even | D18: =C15+(C14*D16) -> 87608.046 | E18: $/year
A21: Scenario Table for Chart
A22: Active Users | B22: PaaS Annual Cost | C22: IaaS Annual Cost | D22: Cheaper Model
A23: 0 | B23: =$B$15+($B$14*A23) -> 2400 | C23: =$C$15+($C$14*A23) -> 30846.49 | D23: =IF(B23<C23,"PaaS","IaaS") -> PaaS
A24: 5000 | B24: =$B$15+($B$14*A24) -> 3992.0223 | C24: =$C$15+($C$14*A24) -> 31907.02 | D24: =IF(B24<C24,"PaaS","IaaS") -> PaaS
A25: 15000 | B25: =$B$15+($B$14*A25) -> 7176.0668 | C25: =$C$15+($C$14*A25) -> 34028.079 | D25: =IF(B25<C25,"PaaS","IaaS") -> PaaS
A26: 50000 | B26: =$B$15+($B$14*A26) -> 18320.223 | C26: =$C$15+($C$14*A26) -> 41451.787 | D26: =IF(B26<C26,"PaaS","IaaS") -> PaaS
A27: 100000 | B27: =$B$15+($B$14*A27) -> 34240.445 | C27: =$C$15+($C$14*A27) -> 52057.083 | D27: =IF(B27<C27,"PaaS","IaaS") -> PaaS
A28: 150000 | B28: =$B$15+($B$14*A28) -> 50160.668 | C28: =$C$15+($C$14*A28) -> 62662.38 | D28: =IF(B28<C28,"PaaS","IaaS") -> PaaS
A29: 200000 | B29: =$B$15+($B$14*A29) -> 66080.89 | C29: =$C$15+($C$14*A29) -> 73267.677 | D29: =IF(B29<C29,"PaaS","IaaS") -> PaaS
A30: 250000 | B30: =$B$15+($B$14*A30) -> 82001.113 | C30: =$C$15+($C$14*A30) -> 83872.973 | D30: =IF(B30<C30,"PaaS","IaaS") -> PaaS
A31: 300000 | B31: =$B$15+($B$14*A31) -> 97921.335 | C31: =$C$15+($C$14*A31) -> 94478.27 | D31: =IF(B31<C31,"PaaS","IaaS") -> IaaS

Sheet Reflection & Recommendation
A1: Reflection and Recommendation
A2: Qualitative factors explain why the lowest infrastructure price is not necessarily the lowest total cost.
A4: Operations Responsibilities
A5: Under IaaS, the operations team owns the guest operating system, runtime and database installation, patches, backups, monitoring, capacity planning, scaling, and much of incident response. Under PaaS, Google manages most infrastructure and database maintenance, while the team focuses on application configuration, observability, access controls, data protection settings, and cost governance. For a small, lean startup, PaaS is generally better because it converts recurring operational work into a managed service and lets engineers spend more time on product delivery.
A9: Security and Compliance
A10: Both models use a shared-responsibility model, but the boundary differs. With IaaS, Fast Growth Inc. must patch and harden the VM operating system, configure database security, validate backups, and maintain monitoring. With PaaS, Google handles more of the underlying patching and service maintenance, making secure defaults and consistent updates easier to apply. The company still remains responsible for identities, application vulnerabilities, secrets, data classification, encryption choices, and e-commerce compliance controls such as PCI DSS scope management.
A14: Portability and Vendor Lock-In
A15: IaaS is typically easier to re-create at another provider because a VM-based stack can use common operating systems, containers, and database engines. PaaS can create greater switching costs through provider-specific deployment settings, IAM, monitoring, autoscaling, and managed database features. However, portability depends on design: containerizing the application, using standard PostgreSQL/MySQL features, managing infrastructure as code, and avoiding proprietary APIs can reduce lock-in in either model.
A19: Recommendation for Fast Growth Inc.
A20: Recommendation: choose PaaS for Year 1 and retain it for Year 2 under the assignment assumptions. The model shows that operations labor overwhelms the small infrastructure savings from self-managing a VM. PaaS is therefore the lower-cost option at 5,000 and 15,000 active users, while also offering faster delivery, simpler scaling, and a smaller patching burden. The linear model estimates that IaaS does not become cheaper until roughly 267,000 active users. Even near that threshold, the company should reconsider the assumptions rather than switch automatically: mature staffing, reliability requirements, reserved-use discounts, architecture efficiency, load balancing, redundancy, and migration risk could materially change the result.
